python_unfuck-1.0.2.dist-info/licenses/LICENSE
unfuck/__init__.py
unfuck/ai/__init__.py
unfuck/ai/ai_analyzer.py
unfuck/ai/ollama_client.py
unfuck/cli/__init__.py
unfuck/cli/main.py
unfuck/cli/personality.py
unfuck/cli/ui.py
unfuck/core/__init__.py
unfuck/core/error_analyzer.py
unfuck/core/error_capture.py
unfuck/core/fix_engine.py
unfuck/core/pattern_database.py
unfuck/utils/__init__.py
unfuck/utils/config.py
unfuck/utils/helpers.py
unfuck/utils/logger.py
python_unfuck-1.0.2.dist-info/METADATA
python_unfuck-1.0.2.dist-info/WHEEL
python_unfuck-1.0.2.dist-info/entry_points.txt
python_unfuck-1.0.2.dist-info/top_level.txt
python_unfuck-1.0.2.dist-info/RECORD
