Metadata-Version: 2.4
Name: python-unfuck
Version: 1.0.2
Summary: 🔥 The magical Python error fixing tool that automatically fixes your code with a single command! Features AI integration, 5 personality modes, and fixes 50+ common errors in under 2 seconds.
Home-page: https://github.com/Sherin-SEF-AI/unfuck
Author: Sherin Joseph
Author-email: Sherin Joseph <sherin.joseph2217@gmail.com>
Maintainer-email: Sherin Joseph <sherin.joseph2217@gmail.com>
License: MIT
Project-URL: Homepage, https://github.com/Sherin-SEF-AI/unfuck
Project-URL: Repository, https://github.com/Sherin-SEF-AI/unfuck
Project-URL: Documentation, https://github.com/Sherin-SEF-AI/unfuck#readme
Project-URL: Bug Tracker, https://github.com/Sherin-SEF-AI/unfuck/issues
Project-URL: LinkedIn, https://www.linkedin.com/in/sherin-roy-deepmost/
Keywords: python,debug,error,fix,automation,tool
Classifier: Development Status :: 4 - Beta
Classifier: Intended Audience :: Developers
Classifier: License :: OSI Approved :: MIT License
Classifier: Operating System :: OS Independent
Classifier: Programming Language :: Python :: 3
Classifier: Programming Language :: Python :: 3.8
Classifier: Programming Language :: Python :: 3.9
Classifier: Programming Language :: Python :: 3.10
Classifier: Programming Language :: Python :: 3.11
Classifier: Programming Language :: Python :: 3.12
Classifier: Topic :: Software Development :: Debuggers
Classifier: Topic :: Software Development :: Quality Assurance
Classifier: Topic :: Software Development :: Libraries :: Python Modules
Requires-Python: >=3.8
License-File: LICENSE
Requires-Dist: colorama>=0.4.4
Requires-Dist: rich>=13.0.0
Requires-Dist: click>=8.0.0
Provides-Extra: ai
Requires-Dist: ollama>=0.1.0; extra == "ai"
Requires-Dist: requests>=2.25.0; extra == "ai"
Provides-Extra: dev
Requires-Dist: pytest>=6.0.0; extra == "dev"
Requires-Dist: pytest-cov>=2.10.0; extra == "dev"
Requires-Dist: black>=21.0.0; extra == "dev"
Requires-Dist: flake8>=3.8.0; extra == "dev"
Dynamic: author
Dynamic: home-page
Dynamic: license-file
Dynamic: requires-python
